README.md
setup.cfg
setup.py
doop/__init__.py
doop/codes.py
doop_codes.egg-info/PKG-INFO
doop_codes.egg-info/SOURCES.txt
doop_codes.egg-info/dependency_links.txt
doop_codes.egg-info/top_level.txt