Metadata-Version: 2.1
Name: doop-codes
Version: 0.0.1
Summary: Search python snippets
Home-page: https://www.doop.codes
Author: doop
Author-email: doopcodes@gmail.com
License: UNKNOWN
Platform: UNKNOWN
Classifier: Programming Language :: Python :: 3
Classifier: License :: OSI Approved :: MIT License
Classifier: Operating System :: OS Independent
Classifier: Topic :: Software Development
Requires-Python: >=2.4
